{
    "name": "Diona",
    "title": "Kätzlein Cocktail",
    "vision": "Cryo",
    "weapon": "Bow",
    "gender": "Female",
    "nation": "Mondstadt",
    "rarity": "4",
    "image": "https://static.wikia.nocookie.net/gensin-impact/images/c/ce/Character_Diona_Portrait.png",
    "constellation": "Feles",
    "birthday": "January 18th",
    "description": "The incredibly popular bartender of the Cat's Tail tavern, rising star of Mondstadt's wine industry, and the greatest challenger to its traditional powerhouses. A feisty feline young lady from Springvale, any drink mixed by Diona's hand tastes delicious beyond belief. Yet given her extreme distaste for alcohol, is her talent a blessing or a curse?",
	"url": "https://genshin-impact.fandom.com/wiki/Diona"
}